falcon_core/__init__.py
falcon_core/__main__.py
falcon_core/middleware.py
falcon_core/resources.py
falcon_core/routes.py
falcon_core/rules.py
falcon_core/utils.py
falcon_core/wsgi.py
falcon_core/bin/falcon-core.py
falcon_core/config/__init__.py
falcon_core/config/global_settings.py
falcon_core/management/__init__.py
falcon_core/management/base.py
falcon_core/management/utils.py
falcon_core/management/commands/__init__.py
falcon_core/management/commands/deploy.py
falcon_core/management/commands/runserver.py
falcon_core/management/commands/startapp.py
falcon_core/management/commands/startproject.py
falcon_core-0.0.28.data/scripts/falcon-core.py
falcon_core-0.0.28.dist-info/LICENSE
falcon_core-0.0.28.dist-info/METADATA
falcon_core-0.0.28.dist-info/WHEEL
falcon_core-0.0.28.dist-info/entry_points.txt
falcon_core-0.0.28.dist-info/top_level.txt
falcon_core-0.0.28.dist-info/RECORD
