Metadata-Version: 2.1
Name: falcon-core
Version: 0.0.28
Summary: Falcon Core Inspired by Django for Falcon API Framework.
Home-page: https://github.com/Maksych/falcon_core
Author: Maksym Sichkaruk
Author-email: maxim.18.08.1997@gmail.com
License: MIT
Platform: UNKNOWN
Classifier: Environment :: Web Environment
Classifier: Intended Audience :: Developers
Classifier: License :: OSI Approved :: BSD License
Classifier: Operating System :: OS Independent
Classifier: Programming Language :: Python
Requires-Dist: falcon
Requires-Dist: waitress
Requires-Dist: gunicorn
